{
  "board": [
    [
      0,
      0,
      0,
      0,
      0,
      0,
      0,
      0,
      0
    ],
    [
      0,
      0,
      0,
      0,
      0,
      0,
      0,
      0,
      0
    ],
    [
      0,
      0,
      0,
      0,
      0,
      0,
      0,
      0,
      0
    ],
    [
      0,
      0,
      0,
      0,
      0,
      0,
      0,
      0,
      0
    ],
    [
      0,
      0,
      0,
      0,
      0,
      0,
      0,
      0,
      0
    ],
    [
      0,
      0,
      0,
      0,
      0,
      0,
      0,
      0,
      0
    ],
    [
      0,
      0,
      0,
      0,
      0,
      0,
      0,
      0,
      0
    ],
    [
      0,
      0,
      0,
      0,
      0,
      0,
      0,
      0,
      0
    ],
    [
      0,
      0,
      1,
      2,
      2,
      1,
      0,
      0,
      0
    ]
  ],
  "current_player": 2,
  "mode": 2,
  "ai_type": null,
  "ai_depth": 3,
  "move_history": [
    [
      8,
      2,
      1
    ],
    [
      8,
      3,
      2
    ],
    [
      8,
      4,
      2
    ],
    [
      8,
      5,
      1
    ]
  ],
  "game_over": false,
  "winner": null,
  "last_move": [
    8,
    5
  ],
  "winning_cells": [],
  "game_id": "6aa5f8c8-f261-495c-a56d-998c7ec29358",
  "timestamp": "2026-03-24T12:07:09.801785"
}