{
  "board": [
    [
      0,
      0,
      0,
      0,
      0,
      0,
      0,
      0,
      0
    ],
    [
      0,
      0,
      0,
      0,
      0,
      0,
      0,
      0,
      0
    ],
    [
      0,
      0,
      0,
      0,
      0,
      0,
      0,
      0,
      0
    ],
    [
      0,
      0,
      0,
      0,
      0,
      0,
      0,
      0,
      0
    ],
    [
      0,
      0,
      0,
      0,
      0,
      0,
      0,
      0,
      0
    ],
    [
      0,
      0,
      0,
      0,
      0,
      0,
      0,
      0,
      0
    ],
    [
      0,
      0,
      0,
      0,
      0,
      0,
      0,
      0,
      0
    ],
    [
      0,
      0,
      0,
      0,
      0,
      0,
      0,
      0,
      0
    ],
    [
      0,
      0,
      0,
      1,
      2,
      0,
      0,
      0,
      0
    ]
  ],
  "current_player": 1,
  "mode": 0,
  "ai_type": "random",
  "ai_depth": 3,
  "move_history": [
    [
      8,
      3,
      1
    ],
    [
      8,
      4,
      2
    ]
  ],
  "game_over": false,
  "winner": null,
  "last_move": [
    8,
    4
  ],
  "winning_cells": [],
  "game_id": "92f90925-dfe2-4da9-a97a-53c25861ad24",
  "timestamp": "2026-03-21T22:18:49.958292"
}